src/MainWindow.py
src/__init__.py
src/debug.py
src/expplot.py
src/utils.py
src/widgets.py
src/labelme_local/__init__.py
src/labelme_local/__main__.py
src/labelme_local/app.py
src/labelme_local/label_file.py
src/labelme_local/logger.py
src/labelme_local/shape.py
src/labelme_local/testing.py
src/labelme_local/wind.py
src/labelme_local/cli/__init__.py
src/labelme_local/cli/draw_json.py
src/labelme_local/cli/draw_label_png.py
src/labelme_local/cli/json_to_dataset.py
src/labelme_local/cli/on_docker.py
src/labelme_local/config/__init__.py
src/labelme_local/utils/__init__.py
src/labelme_local/utils/_io.py
src/labelme_local/utils/image.py
src/labelme_local/utils/qt.py
src/labelme_local/utils/shape.py
src/labelme_local/widgets/__init__.py
src/labelme_local/widgets/brightness_contrast_dialog.py
src/labelme_local/widgets/canvas.py
src/labelme_local/widgets/color_dialog.py
src/labelme_local/widgets/escapable_qlist_widget.py
src/labelme_local/widgets/file_dialog_preview.py
src/labelme_local/widgets/label_dialog.py
src/labelme_local/widgets/label_list_widget.py
src/labelme_local/widgets/tool_bar.py
src/labelme_local/widgets/unique_label_qlist_widget.py
src/labelme_local/widgets/zoom_widget.py
src/yolov_res/__init__.py
src/yolov_res/debug.py
src/yolov_res/detect.py
src/yolov_res/detect_01.py
src/yolov_res/detect_yocls.py
src/yolov_res/detect_yocls_01.py
src/yolov_res/detect_yocls_batch.py
src/yolov_res/detect_yocls_batch_01.py
src/yolov_res/export.py
src/yolov_res/hubconf.py
src/yolov_res/make_prediction.py
src/yolov_res/pipeline.py
src/yolov_res/pipelinetool.py
src/yolov_res/train.py
src/yolov_res/train_2step.py
src/yolov_res/train_django.py
src/yolov_res/val.py
src/yolov_res/val_map.py
src/yolov_res/val_map_01.py
src/yolov_res/model_cls/__init__.py
src/yolov_res/model_cls/cnm.py
src/yolov_res/model_cls/dataset.py
src/yolov_res/model_cls/plot.py
src/yolov_res/model_cls/resnet.py
src/yolov_res/model_cls/train.py
src/yolov_res/models/__init__.py
src/yolov_res/models/common.py
cellscanner-2.3.dist-info/LICENSE
cellscanner-2.3.dist-info/METADATA
cellscanner-2.3.dist-info/WHEEL
cellscanner-2.3.dist-info/entry_points.txt
cellscanner-2.3.dist-info/top_level.txt
cellscanner-2.3.dist-info/RECORD
