Metadata-Version: 2.1
Name: cellscanner
Version: 2.3
Summary: GREAT!!!!!!!!!!
Author: zhw
Author-email: 1353595807@qq.com
License-File: LICENSE
